{
  "code": 200,
  "msg": "操作成功",
  "data": {
    "x_time": [
      "2026-04-16 17:00",
      "2026-04-16 18:00",
      "2026-04-16 19:00",
      "2026-04-16 20:00",
      "2026-04-16 21:00",
      "2026-04-16 22:00",
      "2026-04-16 23:00",
      "2026-04-17 00:00",
      "2026-04-17 01:00",
      "2026-04-17 02:00",
      "2026-04-17 03:00",
      "2026-04-17 04:00",
      "2026-04-17 05:00",
      "2026-04-17 06:00",
      "2026-04-17 07:00",
      "2026-04-17 08:00",
      "2026-04-17 09:00",
      "2026-04-17 10:00",
      "2026-04-17 11:00",
      "2026-04-17 12:00",
      "2026-04-17 13:00",
      "2026-04-17 14:00",
      "2026-04-17 15:00",
      "2026-04-17 16:00"
    ],
    "modelCallCount": [
      112, 85, 74, 7, 0, 21, 149, 61, 0, 0, 0, 0, 0, 0, 0, 38, 180, 58, 12, 0,
      0, 0, 0, 0
    ],
    "tokensUsage": [
      4084694, 3757247, 2908956, 181134, 0, 392109, 8140495, 1621604, 0, 0, 0,
      0, 0, 0, 0, 1218083, 10092888, 3664309, 618699, 0, 0, 0, 0, 0
    ],
    "totalUsage": {
      "totalModelCallCount": 797,
      "totalTokensUsage": 36680218,
      "modelSummaryList": [
        { "modelName": "GLM-5.1", "totalTokens": 58664457, "sortOrder": 1 },
        { "modelName": "GLM-4.7", "totalTokens": 78093, "sortOrder": 2 }
      ]
    },
    "modelDataList": [
      {
        "modelName": "GLM-5.1",
        "sortOrder": 1,
        "tokensUsage": [
          4084694, 3757247, 2908956, 181134, 0, 392109, 8140495, 1621604, 0, 0,
          0, 0, 0, 0, 0, 1218083, 10092888, 3664309, 540606, 0, 0, 0, 0, 0
        ],
        "totalTokens": 58664457
      },
      {
        "modelName": "GLM-4.7",
        "sortOrder": 2,
        "tokensUsage": [
          0, 0, 0, 0, 0, 0, 0, 0, 0, 0, 0, 0, 0, 0, 0, 0, 0, 0, 78093, 0, 0, 0,
          0, 0
        ],
        "totalTokens": 78093
      }
    ],
    "modelSummaryList": [
      { "modelName": "GLM-5.1", "totalTokens": 58664457, "sortOrder": 1 },
      { "modelName": "GLM-4.7", "totalTokens": 78093, "sortOrder": 2 }
    ],
    "granularity": "hourly"
  },
  "success": true
}
